rebyte/__init__.py
rebyte/_rebyte_scripts.py
rebyte/api_requestor.py
rebyte/logger.py
rebyte/rebyte_response.py
rebyte/version.py
rebyte-0.0.9.dist-info/LICENSE
rebyte-0.0.9.dist-info/METADATA
rebyte-0.0.9.dist-info/WHEEL
rebyte-0.0.9.dist-info/entry_points.txt
rebyte-0.0.9.dist-info/top_level.txt
rebyte-0.0.9.dist-info/zip-safe
rebyte-0.0.9.dist-info/RECORD
