Metadata-Version: 2.2
Name: rebyte
Version: 0.0.9
Summary: Python client library for the Rebyte API
Home-page: https://github.com/RebyteAI/rebyte-python
Author: Rebyte team
Author-email: support@rebyte.ai
Classifier: Programming Language :: Python :: 3
Classifier: License :: OSI Approved :: MIT License
Classifier: Operating System :: OS Independent
Requires-Python: >=3.7.1
License-File: LICENSE
Requires-Dist: requests>=2.20
Requires-Dist: typing_extensions; python_version < "3.8"
Requires-Dist: aiohttp
Provides-Extra: dev
Requires-Dist: black~=21.6b0; extra == "dev"
Requires-Dist: pytest==6.*; extra == "dev"
Requires-Dist: pytest-asyncio; extra == "dev"
Requires-Dist: pytest-mock; extra == "dev"
